setup.py
merkletree/__init__.py
merkletree.egg-info/PKG-INFO
merkletree.egg-info/SOURCES.txt
merkletree.egg-info/dependency_links.txt
merkletree.egg-info/not-zip-safe
merkletree.egg-info/requires.txt
merkletree.egg-info/top_level.txt